Metadata-Version: 2.1
Name: hpc-mcp
Version: 0.0.0
Summary: Agentic MCP tools for HPC
Home-page: https://github.com/converged-computing/hpc-mcp
Author: Vanessa Sochat
Author-email: vsoch@users.noreply.github.com
Maintainer: Vanessa Sochat
License: LICENSE
Keywords: mcp,model context protocol,high performance computing,hpc,docker,build,workloads
Classifier: Intended Audience :: Science/Research
Classifier: Intended Audience :: Developers
Classifier: License :: OSI Approved :: MIT License
Classifier: Programming Language :: C
Classifier: Programming Language :: Python
Classifier: Topic :: Software Development
Classifier: Topic :: Scientific/Engineering
Classifier: Operating System :: Unix
Classifier: Programming Language :: Python :: 3.11
License-File: LICENSE
License-File: NOTICE
Requires-Dist: mcp
Requires-Dist: fastmcp
Requires-Dist: rich
Requires-Dist: fastapi
Requires-Dist: pyyaml
Requires-Dist: ply
Provides-Extra: all
Requires-Dist: mcp ; extra == 'all'
Requires-Dist: fastmcp ; extra == 'all'
Requires-Dist: rich ; extra == 'all'
Requires-Dist: fastapi ; extra == 'all'
Requires-Dist: pyyaml ; extra == 'all'
Requires-Dist: ply ; extra == 'all'
Requires-Dist: pytest >=4.6.2 ; extra == 'all'
Requires-Dist: pytest-asyncio ; extra == 'all'
